Workbook

Sheet Assumptions
A1: ITV Capital Structure Model — Assumptions
A2: Analysis date: 15 September 2026
A4: Revenue growth FY2026E | B4: 0.01 | C4: H1 2026 guidance: 1% growth
A5: Revenue growth FY2027E | B5: 0.01 | C5: Medium-term assumption
A6: Revenue growth FY2028E | B6: 0.01 | C6: Medium-term assumption
A7: Adjusted EBITA margin | B7: 0.152 | C7: FY2025 actual; within guided range
A8: Depreciation | B8: 48 | C8: FY2025 actual
A9: Adjusted financing costs | B9: 40 | C9: FY2026 guidance
A10: Effective tax rate | B10: 0.27 | C10: FY2026 guidance
A11: Profit-to-cash conversion | B11: 0.8 | C11: Medium-term guidance
A12: Dividend per share (pence) | B12: 5 | C12: FY2026 guidance
A13: Shares outstanding (m) | B13: 3752 | C13: H1 2026 report weighted avg
A14: Opening net debt FY2025 (reported) | B14: 566 | C14: FY2025 annual report
A15: Currency swap adjustment | B15: -8 | C15: Reconciliation difference
A17: Note: Profit-to-cash conversion reflects ITV's medium-term guidance of ~80% adjusted cash flow / adjusted EBITA. FY2025 was 65% due to working capital build in ITV Studios; FY2026 guidance points to normalisation.

Sheet Historicals
A1: Historical Financials
A2: £m unless stated
B3: 2024A | C3: 2025A | D3: 2026H1A
A4: Revenue | B4: 3488 | C4: 3511 | D4: 1603
A5: Adjusted EBITA | B5: 542 | C5: 534 | D5: 146
A6: Adjusted EBITA margin | B6: 0.155 | C6: 0.152 | D6: 0.091
A7: Covenant adjusted EBITDA | B7: 548 | C7: 555 | D7: 555
A8: Adjusted financing costs | B8: 25 | C8: 43 | D8: 20
A9: Cash tax paid | B9: 27 | C9: 35 | D9: 25
A10: Capex | B10: 49 | C10: 54 | D10: 26
A11: Dividends paid | B11: 198 | C11: 187 | D11: 124
A12: Operating cash flow | B12: 333 | C12: 202 | D12: 75
A13: Free cash flow | B13: 325 | C13: 187 | D13: 40
A14: Cash | B14: 427 | C14: 302 | D14: 264
A15: Gross debt (loans & facilities) | B15: 733 | C15: 765 | D15: 807
... A17: Reported net debt | B17: 431 | C17: 566 | D17: 652
A18: Net debt / covenant adj EBITDA | B18: 0.8x | C18: 1.0x | D18: 1.0x

Sheet Forecast
A1: Forecast Model | F1: Note: Base case assumes ITV continues as a combined entity. The M&E sale to Sky (announced 6 July 2026, expected completion H2 2027) is treated as strategic context, not modelled into base-case financing.
A2: Analysis date: 15 September 2026
A3: P&L (£m)
A4: Revenue | B4: =Historicals!C4*(1+Assumptions!$B$4) -> 3546.11 | C4: =B4*(1+Assumptions!$B$5) -> 3581.5711 | D4: =C4*(1+Assumptions!$B$6) -> 3617.3868
A5: Adjusted EBITA | B5: =B4*Assumptions!$B$7 -> 539.00872 | C5: =C4*Assumptions!$B$7 -> 544.39881 | D5: =D4*Assumptions!$B$7 -> 549.8428
A6: Adjusted EBITA margin | B6: =B5/B4 -> 0.152 | C6: =C5/C4 -> 0.152 | D6: =D5/D4 -> 0.152
A7: Depreciation | B7: =Assumptions!$B$8 -> 48 | C7: =Assumptions!$B$8 -> 48 | D7: =Assumptions!$B$8 -> 48
A8: Covenant adjusted EBITDA | B8: =B5+B7 -> 587.00872 | C8: =C5+C7 -> 592.39881 | D8: =D5+D7 -> 597.8428
A10: Cash bridge (£m)
A11: Adjusted EBITA | B11: =B5 -> 539.00872 | C11: =C5 -> 544.39881 | D11: =D5 -> 549.8428
A12: Profit-to-cash conversion | B12: =Assumptions!$B$11 -> 0.8 | C12: =Assumptions!$B$11 -> 0.8 | D12: =Assumptions!$B$11 -> 0.8
A13: Adjusted cash flow | B13: =B11*B12 -> 431.20698 | C13: =C11*C12 -> 435.51905 | D13: =D11*D12 -> 439.87424
A14: Cash financing costs | B14: =-Assumptions!$B$9 -> -40 | C14: =-Assumptions!$B$9 -> -40 | D14: =-Assumptions!$B$9 -> -40
A15: Cash tax paid | B15: =-B5*Assumptions!$B$10 -> -145.53235 | C15: =-C5*Assumptions!$B$10 -> -146.98768 | D15: =-D5*Assumptions!$B$10 -> -148.45755
A16: Pension funding | B16: =-3 -> -3 | C16: =-3 -> -3 | D16: =-3 -> -3
A17: Free cash flow | B17: =SUM(B13:B16) -> 242.67462 | C17: =SUM(C13:C16) -> 245.53137 | D17: =SUM(D13:D16) -> 248.41668
A19: Distributions & net debt (£m)
A20: Dividend per share (pence) | B20: =Assumptions!$B$12 -> 5 | C20: =Assumptions!$B$12 -> 5 | D20: =Assumptions!$B$12 -> 5
A21: Shares outstanding (m) | B21: =Assumptions!$B$13 -> 3752 | C21: =Assumptions!$B$13 -> 3752 | D21: =Assumptions!$B$13 -> 3752
A22: Total dividends | B22: =-B20*B21/100 -> -187.6 | C22: =-C20*C21/100 -> -187.6 | D22: =-D20*D21/100 -> -187.6
A23: FCF after dividends | B23: =B17+B22 -> 55.074622 | C23: =C17+C22 -> 57.931368 | D23: =D17+D22 -> 60.816681
A25: Opening net debt | B25: =-Assumptions!$B$14 -> -566 | C25: =B27 -> -510.92538 | D25: =C27 -> -452.99401
A26: Net debt movement | B26: =B23 -> 55.074622 | C26: =C23 -> 57.931368 | D26: =D23 -> 60.816681
A27: Closing net debt | B27: =B25+B26 -> -510.92538 | C27: =C25+C26 -> -452.99401 | D27: =D25+D26 -> -392.17733
A29: Credit metrics
A30: Covenant adjusted EBITDA | B30: =B8 -> 587.00872 | C30: =C8 -> 592.39881 | D30: =D8 -> 597.8428
A31: Net debt / adj EBITDA | B31: =-B27/B30 -> 0.87038806 | C31: =-C27/C30 -> 0.76467745 | D31: =-D27/D30 -> 0.65598738

Sheet Debt & Liquidity

Sheet Options

Sheet Summary
